<annotation>
	<folder>images</folder>
	<filename>000024.jpg</filename>
	<path>D:\yolov5\VOCData\images\000024.jpg</path>
	<source>
		<database>Unknown</database>
	</source>
	<size>
		<width>690</width>
		<height>460</height>
		<depth>3</depth>
	</size>
	<segmented>0</segmented>
	<object>
		<name>smoking</name>
		<pose>Unspecified</pose>
		<truncated>1</truncated>
		<difficult>0</difficult>
		<bndbox>
			<xmin>1</xmin>
			<ymin>385</ymin>
			<xmax>119</xmax>
			<ymax>452</ymax>
		</bndbox>
	</object>
</annotation>
