<annotation>
	<folder>Smoke</folder>
	<filename>smoke10.jpg</filename>
	<path>C:\Users\32631\project\Smoke\smoke10.jpg</path>
	<source>
		<database>Unknown</database>
	</source>
	<size>
		<width>360</width>
		<height>360</height>
		<depth>3</depth>
	</size>
	<segmented>0</segmented>
	<object>
		<name>smoking</name>
		<pose>Unspecified</pose>
		<truncated>0</truncated>
		<difficult>0</difficult>
		<bndbox>
			<xmin>23</xmin>
			<ymin>198</ymin>
			<xmax>94</xmax>
			<ymax>246</ymax>
		</bndbox>
	</object>
</annotation>
