<annotation>
	<folder>Smoke</folder>
	<filename>smoke22.jpg</filename>
	<path>C:\Users\32631\project\Smoke\smoke22.jpg</path>
	<source>
		<database>Unknown</database>
	</source>
	<size>
		<width>640</width>
		<height>334</height>
		<depth>3</depth>
	</size>
	<segmented>0</segmented>
	<object>
		<name>smoking</name>
		<pose>Unspecified</pose>
		<truncated>0</truncated>
		<difficult>0</difficult>
		<bndbox>
			<xmin>267</xmin>
			<ymin>205</ymin>
			<xmax>311</xmax>
			<ymax>269</ymax>
		</bndbox>
	</object>
	<object>
		<name>smoking</name>
		<pose>Unspecified</pose>
		<truncated>0</truncated>
		<difficult>0</difficult>
		<bndbox>
			<xmin>467</xmin>
			<ymin>221</ymin>
			<xmax>493</xmax>
			<ymax>268</ymax>
		</bndbox>
	</object>
</annotation>
