<annotation>
	<folder>Smoke</folder>
	<filename>smoke_a995.jpg</filename>
	<path>C:\Users\32631\project\Smoke\smoke_a995.jpg</path>
	<source>
		<database>Unknown</database>
	</source>
	<size>
		<width>101</width>
		<height>113</height>
		<depth>3</depth>
	</size>
	<segmented>0</segmented>
	<object>
		<name>smoking</name>
		<pose>Unspecified</pose>
		<truncated>0</truncated>
		<difficult>0</difficult>
		<bndbox>
			<xmin>37</xmin>
			<ymin>36</ymin>
			<xmax>66</xmax>
			<ymax>80</ymax>
		</bndbox>
	</object>
</annotation>
